dataset_down/__init__.py
dataset_down/cli.py
dataset_down/api/AuthApi.py
dataset_down/api/__init__.py
dataset_down/client/AuthClient.py
dataset_down/client/__init__.py
dataset_down/config/__init__.py
dataset_down/config/constants.py
dataset_down/config/login_config.py
dataset_down/config/path_config.py
dataset_down/downloader/__init__.py
dataset_down/downloader/downloader.py
dataset_down/exception/IncompleteReadException.py
dataset_down/exception/InterruptExcepiton.py
dataset_down/exception/__init__.py
dataset_down/log/__init__.py
dataset_down/log/logger.py
dataset_down/update/__init__.py
dataset_down/update/sdk_version.py
dataset_down/update/update_check.py
dataset_down/utils/__init__.py
dataset_down/utils/common_utils.py
dataset_down/utils/file.py
dataset_down/utils/http_utils.py
dataset_down/utils/retryable.py
dataset_down/utils/speed_calculator.py
dataset_down/utils/system_utils.py
dataset_down/utils/time_utils.py
jsdataset_down_test-0.28.0.dist-info/METADATA
jsdataset_down_test-0.28.0.dist-info/WHEEL
jsdataset_down_test-0.28.0.dist-info/entry_points.txt
jsdataset_down_test-0.28.0.dist-info/top_level.txt
jsdataset_down_test-0.28.0.dist-info/RECORD
