Metadata-Version: 2.1
Name: jsdataset-down-test
Version: 0.28.0
Summary: A SDK for file downloading with resumable and multi-threaded features.
Home-page: https://github.com/yourname/****
Author: 
Author-email: your.email@example.com
License: UNKNOWN
Platform: UNKNOWN
Classifier: Programming Language :: Python :: 3
Classifier: License :: OSI Approved :: MIT License
Classifier: Operating System :: OS Independent
Requires-Dist: requests
Requires-Dist: tqdm
Requires-Dist: click
Requires-Dist: psutil
Requires-Dist: pytz
